llpyspin/__init__.py
llpyspin/_processes.py
llpyspin/_properties.py
llpyspin/_spinnaker.py
llpyspin/primary.py
llpyspin/recording.py
llpyspin/secondary.py
llpyspin/streaming.py
parallel_pyspin-0.2.dev3.dist-info/LICENSE
parallel_pyspin-0.2.dev3.dist-info/METADATA
parallel_pyspin-0.2.dev3.dist-info/WHEEL
parallel_pyspin-0.2.dev3.dist-info/top_level.txt
parallel_pyspin-0.2.dev3.dist-info/RECORD
