Metadata-Version: 2.1
Name: parallel-pyspin
Version: 0.2.dev3
Summary: parallel and synchronous video acqusition with FLIR USB3 cameras
Home-page: https://github.com/jbhunt/parallel-pyspin
Author: Joshua Hunt
Author-email: hunt.brian.joshua@gmail.com
License: UNKNOWN
Platform: UNKNOWN
Classifier: Programming Language :: Python :: 3
Classifier: License :: OSI Approved :: MIT License
Classifier: Operating System :: OS Independent
Requires-Python: >=3.6
Requires-Dist: pyyaml
Requires-Dist: numpy
